pyclef/__init__.py
pyclef-0.1.2.dist-info/METADATA
pyclef-0.1.2.dist-info/WHEEL
pyclef-0.1.2.dist-info/RECORD
