Metadata-Version: 2.3
Name: pyclef
Version: 0.1.2
Summary: 
Author: Vinícius Fernandes
Author-email: 135647686+viniciusfs14@users.noreply.github.com
Requires-Python: >=3.10
Classifier: Programming Language :: Python :: 3
Classifier: Programming Language :: Python :: 3.10
Classifier: Programming Language :: Python :: 3.11
Classifier: Programming Language :: Python :: 3.12
Classifier: Programming Language :: Python :: 3.13
